openbb_fmp/__init__.py
openbb_fmp/models/__init__.py
openbb_fmp/models/analyst_estimates.py
openbb_fmp/models/available_indices.py
openbb_fmp/models/balance_sheet.py
openbb_fmp/models/balance_sheet_growth.py
openbb_fmp/models/calendar_dividend.py
openbb_fmp/models/calendar_earnings.py
openbb_fmp/models/calendar_events.py
openbb_fmp/models/calendar_ipo.py
openbb_fmp/models/calendar_splits.py
openbb_fmp/models/cash_flow.py
openbb_fmp/models/cash_flow_growth.py
openbb_fmp/models/company_filings.py
openbb_fmp/models/company_news.py
openbb_fmp/models/crypto_historical.py
openbb_fmp/models/crypto_search.py
openbb_fmp/models/currency_historical.py
openbb_fmp/models/currency_pairs.py
openbb_fmp/models/currency_snapshots.py
openbb_fmp/models/discovery_filings.py
openbb_fmp/models/earnings_call_transcript.py
openbb_fmp/models/economic_calendar.py
openbb_fmp/models/equity_gainers.py
openbb_fmp/models/equity_historical.py
openbb_fmp/models/equity_losers.py
openbb_fmp/models/equity_most_active.py
openbb_fmp/models/equity_ownership.py
openbb_fmp/models/equity_peers.py
openbb_fmp/models/equity_profile.py
openbb_fmp/models/equity_quote.py
openbb_fmp/models/equity_screener.py
openbb_fmp/models/esg_score.py
openbb_fmp/models/etf_countries.py
openbb_fmp/models/etf_equity_exposure.py
openbb_fmp/models/etf_holdings.py
openbb_fmp/models/etf_info.py
openbb_fmp/models/etf_search.py
openbb_fmp/models/etf_sectors.py
openbb_fmp/models/executive_compensation.py
openbb_fmp/models/financial_ratios.py
openbb_fmp/models/forward_ebitda_estimates.py
openbb_fmp/models/forward_eps_estimates.py
openbb_fmp/models/government_trades.py
openbb_fmp/models/historical_dividends.py
openbb_fmp/models/historical_employees.py
openbb_fmp/models/historical_eps.py
openbb_fmp/models/historical_market_cap.py
openbb_fmp/models/historical_splits.py
openbb_fmp/models/income_statement.py
openbb_fmp/models/income_statement_growth.py
openbb_fmp/models/index_constituents.py
openbb_fmp/models/index_historical.py
openbb_fmp-1.5.0.dist-info/METADATA
openbb_fmp-1.5.0.dist-info/WHEEL
openbb_fmp-1.5.0.dist-info/entry_points.txt
openbb_fmp-1.5.0.dist-info/RECORD
